benchmarks/__init__.py
benchmarks/benchmarks.py
doc/Makefile
doc/api.rst
doc/conf.py
doc/index.rst
doc/requirements.txt
doc/_static/git.png
doc/_static/logo.png
doc/_templates/class.rst
doc/_templates/function.rst
doc/sphinxext/docscrape.py
doc/sphinxext/docscrape_sphinx.py
doc/sphinxext/github.py
doc/sphinxext/math_dollar.py
doc/sphinxext/numpydoc.py
examples/README.txt
examples/G2/README.txt
examples/G2/bootstrap.py
examples/G2/jackknife.py
examples/fake_data/README.txt
examples/fake_data/fake_map.fits
examples/fake_data/fake_map.py
examples/fake_data/plot_basic_usage.py
nikamap/__init__.py
nikamap/_version.py
nikamap/analysis.py
nikamap/contmap.py
nikamap/due.py
nikamap/nikamap.py
nikamap/utils.py
nikamap/version.py
nikamap/data/README.rst
nikamap/tests/__init__.py
nikamap/tests/test_analysis.py
nikamap/tests/test_contmap.py
nikamap/tests/test_nikamap.py
nikamap/tests/test_utils.py
nikamap/tests/baseline/test_contmap_check_SNR_ax.png
nikamap/tests/baseline/test_contmap_plot_PSD_grid_sources.png
nikamap/tests/baseline/test_contmap_plot_PSD_single_source.png
nikamap/tests/baseline/test_contmap_plot_PSD_single_source_mask.png
nikamap/tests/baseline/test_contmap_plot_PSD_single_source_side.png
nikamap/tests/baseline/test_contmap_plot_PSD_wobble_grid_sources.png
nikamap/tests/baseline/test_contmap_plot_SNR_ax_grid_sources.png
nikamap/tests/baseline/test_contmap_plot_SNR_ax_single_source.png
nikamap/tests/baseline/test_contmap_plot_SNR_ax_single_source_mask.png
nikamap/tests/baseline/test_contmap_plot_SNR_ax_single_source_side.png
nikamap/tests/baseline/test_contmap_plot_SNR_ax_wobble_grid_sources.png
nikamap/tests/baseline/test_contmap_plot_SNR_grid_sources.png
nikamap/tests/baseline/test_contmap_plot_SNR_single_source.png
nikamap/tests/baseline/test_contmap_plot_SNR_single_source_mask.png
nikamap/tests/baseline/test_contmap_plot_SNR_single_source_side.png
nikamap/tests/baseline/test_contmap_plot_SNR_wobble_grid_sources.png
nikamap-1.2.dist-info/LICENSE
nikamap-1.2.dist-info/METADATA
nikamap-1.2.dist-info/WHEEL
nikamap-1.2.dist-info/entry_points.txt
nikamap-1.2.dist-info/top_level.txt
nikamap-1.2.dist-info/RECORD
