Metadata-Version: 2.1
Name: nikamap
Version: 1.2
Summary: nikamap: a package to manipulate data produced by the IDL NIKA2 pipeline
Author-email: Alexandre Beelen <alexandre.beelen@lam.fr>
License: The MIT License (MIT)
Project-URL: repository, http://github.com/abeelen/nikamap
Classifier: Development Status :: 3 - Alpha
Classifier: Environment :: Console
Classifier: Intended Audience :: Science/Research
Classifier: License :: OSI Approved :: MIT License
Classifier: Operating System :: OS Independent
Classifier: Programming Language :: Python
Classifier: Topic :: Scientific/Engineering
Requires-Python: >=3.10
License-File: LICENSE
Requires-Dist: numpy
Requires-Dist: scipy
Requires-Dist: matplotlib
Requires-Dist: astropy>5.3
Requires-Dist: photutils>=1.13
Requires-Dist: scikit-image
Requires-Dist: powspec>=0.3
Provides-Extra: docs
Requires-Dist: sphinx; extra == "docs"
Requires-Dist: sphinx-automodapi; extra == "docs"
Requires-Dist: sphinx-gallery; extra == "docs"
Provides-Extra: stacking
Requires-Dist: reproject; extra == "stacking"
Provides-Extra: test
Requires-Dist: pytest; extra == "test"
Requires-Dist: pytest-doctestplus; extra == "test"
Requires-Dist: pytest-cov; extra == "test"
Requires-Dist: pytest-mpl; extra == "test"
Requires-Dist: reproject; extra == "test"
